pyhydroportail/__init__.py
pyhydroportail/const.py
pyhydroportail/utils.py
pyhydroportail/actions/__init__.py
pyhydroportail/actions/export.py
pyhydroportail/actions/hcrm.py
pyhydroportail/actions/info.py
pyhydroportail/actions/search.py
pyhydroportail/commands/__init__.py
pyhydroportail/commands/arguments.py
pyhydroportail/commands/pyhydro.py
pyhydroportail/core/HydroProject.py
pyhydroportail/core/HydroSerieStation.py
pyhydroportail-0.0.2rc0.dist-info/METADATA
pyhydroportail-0.0.2rc0.dist-info/WHEEL
pyhydroportail-0.0.2rc0.dist-info/entry_points.txt
pyhydroportail-0.0.2rc0.dist-info/top_level.txt
pyhydroportail-0.0.2rc0.dist-info/RECORD
