Metadata-Version: 2.1
Name: pyhydroportail
Version: 0.0.2rc0
Summary: My package description
Author-email: Nicolas Godet <contact@nicodet.fr>
License: BSD-3-Clause
Project-URL: source, https://gitlab.nicodet.fr/nicogodet/pyhydroportail
Project-URL: download, https://pypi.org/project/pyhydroportail/#files
Project-URL: tracker, https://gitlab.nicodet.fr/nicogodet/pyhydroportail/-/issues
Keywords: one,two
Classifier: Development Status :: 2 - Pre-Alpha
Classifier: Environment :: Console
Classifier: Intended Audience :: Science/Research
Classifier: License :: OSI Approved :: GNU General Public License v3 (GPLv3)
Classifier: Natural Language :: French
Classifier: Programming Language :: Python
Classifier: Topic :: Scientific/Engineering :: Hydrology
Requires-Python: >=3.7
Requires-Dist: requests
Requires-Dist: openpyxl
Requires-Dist: pandas
